[
	{
		"name": "$construct",
		"ident": 1,
		"order": 1,
		"pvardefs": [
			{
				"name": "pEditRef",
				"order": 1,
				"type": "kItemref",
				"subtype": "",
				"sublen": 0,
				"param": 1
			},
			{
				"name": "pDocName",
				"order": 2,
				"type": "kCharacter",
				"subtype": "kSimplechar",
				"sublen": 100000000,
				"param": 2
			},
			{
				"name": "pGroupName",
				"order": 3,
				"type": "kCharacter",
				"subtype": "kSimplechar",
				"sublen": 100000000,
				"param": 3
			}
		],
		"lvardefs": [

		]
	},
	{
		"name": "$destruct",
		"ident": 2,
		"order": 2,
		"pvardefs": [

		],
		"lvardefs": [

		]
	},
	{
		"name": "$openurl",
		"ident": 4,
		"order": 3,
		"desc": "23_09_2011_CHANGE_1 new method",
		"pvardefs": [
			{
				"name": "pTheURL",
				"order": 1,
				"type": "kCharacter",
				"subtype": "kSimplechar",
				"sublen": 100000000,
				"param": 1,
				"desc": "fully qualified URL"
			}
		],
		"lvardefs": [

		]
	},
	{
		"name": "$opendocument",
		"ident": 5,
		"order": 4,
		"pvardefs": [
			{
				"name": "pDocName",
				"order": 1,
				"type": "kCharacter",
				"subtype": "kSimplechar",
				"sublen": 100000000,
				"param": 1
			},
			{
				"name": "pSubHeader",
				"order": 2,
				"type": "kCharacter",
				"subtype": "kSimplechar",
				"sublen": 100000000,
				"param": 2
			},
			{
				"name": "pText",
				"order": 3,
				"type": "kCharacter",
				"subtype": "kSimplechar",
				"sublen": 100000000,
				"param": 3
			}
		],
		"lvardefs": [

		]
	},
	{
		"name": "$owrite_export",
		"ident": 3,
		"order": 5,
		"pvardefs": [
			{
				"name": "pExpFormat",
				"order": 1,
				"type": "kCharacter",
				"subtype": "kSimplechar",
				"sublen": 100000000,
				"param": 1,
				"desc": "Currently only 'html'"
			},
			{
				"name": "pExpType",
				"order": 2,
				"type": "kCharacter",
				"subtype": "kSimplechar",
				"sublen": 100000000,
				"param": 2,
				"desc": "Either 'href' or 'src'"
			}
		],
		"lvardefs": [
			{
				"name": "linkCalc",
				"order": 11,
				"type": "kCharacter",
				"subtype": "kSimplechar",
				"sublen": 100000000
			},
			{
				"name": "linkResult",
				"order": 12,
				"type": "kCharacter",
				"subtype": "kSimplechar",
				"sublen": 100000000
			},
			{
				"name": "pictChecksum",
				"order": 8,
				"type": "kInteger",
				"subtype": "k32bitint",
				"sublen": 0
			},
			{
				"name": "pictCID",
				"order": 6,
				"type": "kCharacter",
				"subtype": "kSimplechar",
				"sublen": 100000000
			},
			{
				"name": "pictData",
				"order": 3,
				"type": "kBinary",
				"subtype": 0,
				"sublen": 100000000
			},
			{
				"name": "pictFormat",
				"order": 4,
				"type": "kCharacter",
				"subtype": "kSimplechar",
				"sublen": 100000000
			},
			{
				"name": "pictLineNo",
				"order": 9,
				"type": "kInteger",
				"subtype": "k32bitint",
				"sublen": 0
			},
			{
				"name": "pictName",
				"order": 5,
				"type": "kCharacter",
				"subtype": "kSimplechar",
				"sublen": 100000000
			},
			{
				"name": "pictSubType",
				"order": 7,
				"type": "kCharacter",
				"subtype": "kSimplechar",
				"sublen": 100000000
			}
		]
	},
	{
		"name": "sendMail",
		"ident": 0,
		"order": 6,
		"pvardefs": [

		],
		"lvardefs": [
			{
				"name": "attempts",
				"order": 18,
				"type": "kInteger",
				"subtype": "k32bitint",
				"sublen": 0
			},
			{
				"name": "lastLine",
				"order": 14,
				"type": "kInteger",
				"subtype": "k32bitint",
				"sublen": 0
			},
			{
				"name": "lBinData",
				"order": 6,
				"type": "kBinary",
				"subtype": 0,
				"sublen": 100000000
			},
			{
				"name": "lCharData",
				"order": 5,
				"type": "kCharacter",
				"subtype": "kSimplechar",
				"sublen": 100000000
			},
			{
				"name": "lCharSet",
				"order": 7,
				"type": "kCharacter",
				"subtype": "kSimplechar",
				"sublen": 100000000
			},
			{
				"name": "lContentSubType",
				"order": 3,
				"type": "kCharacter",
				"subtype": "kSimplechar",
				"sublen": 100000000
			},
			{
				"name": "lContentType",
				"order": 2,
				"type": "kCharacter",
				"subtype": "kSimplechar",
				"sublen": 100000000
			},
			{
				"name": "lDisposition",
				"order": 13,
				"type": "kCharacter",
				"subtype": "kSimplechar",
				"sublen": 100000000
			},
			{
				"name": "lEncoding",
				"order": 8,
				"type": "kCharacter",
				"subtype": "kSimplechar",
				"sublen": 100000000
			},
			{
				"name": "lFileName",
				"order": 4,
				"type": "kCharacter",
				"subtype": "kSimplechar",
				"sublen": 100000000
			},
			{
				"name": "lHtmlData",
				"order": 16,
				"type": "kBinary",
				"subtype": 0,
				"sublen": 100000000
			},
			{
				"name": "lHtmlEncoding",
				"order": 17,
				"type": "kCharacter",
				"subtype": "kSimplechar",
				"sublen": 100000000
			},
			{
				"name": "lLevel",
				"order": 1,
				"type": "kInteger",
				"subtype": "k32bitint",
				"sublen": 0
			},
			{
				"name": "lPlainTextData",
				"order": 15,
				"type": "kCharacter",
				"subtype": "kSimplechar",
				"sublen": 100000000
			},
			{
				"name": "lRef",
				"order": 11,
				"type": "kItemref",
				"subtype": "",
				"sublen": 0
			},
			{
				"name": "lXtraHdrs",
				"order": 12,
				"type": "kList",
				"subtype": "",
				"sublen": 0
			},
			{
				"name": "savedEvalLocal",
				"order": 9,
				"type": "kBoolean",
				"subtype": 0,
				"sublen": 0
			},
			{
				"name": "status",
				"order": 10,
				"type": "kInteger",
				"subtype": "k32bitint",
				"sublen": 0
			},
			{
				"name": "time",
				"order": 19,
				"type": "kInteger",
				"subtype": "k64bitint",
				"sublen": 0
			}
		]
	},
	{
		"name": "$smtpstatusproc",
		"ident": 7,
		"order": 8,
		"pvardefs": [

		],
		"lvardefs": [

		]
	}
]
