{
	"ident": 1051,
	"order": 37,
	"objtype": "kRadio",
	"properties": {
		"active": true,
		"align": "kRightJst",
		"alpha": 255,
		"backcolor": "kColorDefault",
		"backgroundtheme": "kBGThemeParent",
		"backpattern": 0,
		"bordercolor": "kColorDefault",
		"buttonstyle": "kHeadingButton",
		"candropcursor": 0,
		"contextmenu": "",
		"cursor": 0,
		"dataname": "#2",
		"desgroup": 0,
		"designactive": true,
		"deslock": false,
		"disablefocus": false,
		"dragborder": false,
		"dragiconid": 0,
		"dragmode": "kNoDragging",
		"dragrange": "kRangeAll",
		"dropmode": "kAcceptNone",
		"edgefloat": "kEFnone",
		"enabled": true,
		"fieldstyle": "CtrlCheckBox",
		"font": 9,
		"fontsize": 15,
		"fontstyle": "kPlain",
		"forecolor": "kColorDefault",
		"height": 22,
		"helpfile": 0,
		"iconid": "k16x16+10008",
		"keyevents": false,
		"left": 138,
		"local": false,
		"mouseevents": false,
		"nodropcursor": 0,
		"nogray": false,
		"objlink": 4,
		"rmouseevents": false,
		"statusevents": false,
		"subwindowstyle": false,
		"text": "",
		"textcolor": "kColorDefault",
		"tooltip": {
			"type": 0,
			"calc": "Double Line Spacing"
		},
		"top": 31,
		"userinfo": "iFRefOWrite.$curlinespacing",
		"vertcentertext": false,
		"visible": true,
		"width": 22
	}
}
