{
	"ident": 1135,
	"order": 41,
	"objtype": "kRadio",
	"properties": {
		"active": true,
		"align": "kLeftJst",
		"alpha": 255,
		"backcolor": "kColorDefault",
		"backgroundtheme": "kBGThemeWindow",
		"backpattern": 0,
		"bordercolor": "kColorDefault",
		"buttonstyle": "kNoBorderButton",
		"candropcursor": 0,
		"contextmenu": "",
		"cursor": 0,
		"dataname": "ivParams.BkgImgScale",
		"desgroup": 0,
		"designactive": true,
		"deslock": false,
		"disablefocus": false,
		"dragborder": false,
		"dragiconid": 0,
		"dragmode": "kNoDragging",
		"dragrange": "kRangeAll",
		"dropmode": "kAcceptNone",
		"edgefloat": "kEFnone",
		"enabled": true,
		"fieldstyle": "CtrlRadioButton",
		"font": 4,
		"fontsize": 9,
		"fontstyle": "kPlain",
		"forecolor": "kColorDefault",
		"height": 18,
		"helpfile": 0,
		"iconid": 0,
		"keyevents": false,
		"left": 34,
		"local": false,
		"mouseevents": false,
		"nodropcursor": 0,
		"nogray": false,
		"objlink": 196609,
		"rmouseevents": false,
		"statusevents": false,
		"subwindowstyle": false,
		"text": {
			"type": 0,
			"calc": "Scale image to fit page"
		},
		"textcolor": "kColorDefault",
		"tooltip": {
			"type": 0,
			"calc": "Select this option to scale the image to make it fit the page"
		},
		"top": 193,
		"userinfo": "",
		"vertcentertext": false,
		"visible": true,
		"width": 180
	}
}
