[
	{
		"name": "$construct",
		"ident": 0,
		"order": 1,
		"pvardefs": [

		],
		"lvardefs": [
			{
				"name": "dir",
				"order": 1,
				"type": "kCharacter",
				"subtype": "kSimplechar",
				"sublen": 100000000
			},
			{
				"name": "drive",
				"order": 2,
				"type": "kCharacter",
				"subtype": "kSimplechar",
				"sublen": 100000000
			},
			{
				"name": "ext",
				"order": 3,
				"type": "kCharacter",
				"subtype": "kSimplechar",
				"sublen": 100000000
			},
			{
				"name": "name",
				"order": 4,
				"type": "kCharacter",
				"subtype": "kSimplechar",
				"sublen": 100000000
			}
		]
	},
	{
		"name": "$destruct",
		"ident": 1,
		"order": 2,
		"pvardefs": [

		],
		"lvardefs": [

		]
	},
	{
		"name": "-- methods called during construct/destruct",
		"ident": 18,
		"order": 3,
		"pvardefs": [

		],
		"lvardefs": [

		],
		"empty": true
	},
	{
		"name": "construct_examples",
		"ident": 21,
		"order": 4,
		"pvardefs": [

		],
		"lvardefs": [

		]
	},
	{
		"name": "construct_PDFDevice",
		"ident": 12,
		"order": 5,
		"pvardefs": [

		],
		"lvardefs": [
			{
				"name": "deviceParms",
				"order": 5,
				"type": "kRow",
				"subtype": "",
				"sublen": 0
			},
			{
				"name": "OuFontName",
				"order": 2,
				"type": "kCharacter",
				"subtype": "kSimplechar",
				"sublen": 255
			},
			{
				"name": "OuFontSize",
				"order": 3,
				"type": "kInteger",
				"subtype": "k32bitint",
				"sublen": 0
			},
			{
				"name": "OuFontStyle",
				"order": 4,
				"type": "kInteger",
				"subtype": "k32bitint",
				"sublen": 0
			},
			{
				"name": "OuList",
				"order": 1,
				"type": "kList",
				"subtype": "",
				"sublen": 0
			}
		]
	},
	{
		"name": "construct_OSpell2",
		"ident": 15,
		"order": 6,
		"pvardefs": [

		],
		"lvardefs": [

		]
	},
	{
		"name": "construct_OWrite",
		"ident": 16,
		"order": 7,
		"pvardefs": [

		],
		"lvardefs": [
			{
				"name": "fontmapList",
				"order": 4,
				"type": "kList",
				"subtype": "",
				"sublen": 0
			},
			{
				"name": "fontmapRestrictFonts",
				"order": 1,
				"type": "kBoolean",
				"subtype": 0,
				"sublen": 0
			},
			{
				"name": "ok",
				"order": 3,
				"type": "kBoolean",
				"subtype": 0,
				"sublen": 0
			}
		]
	},
	{
		"name": "destruct_examples",
		"ident": 22,
		"order": 9,
		"pvardefs": [

		],
		"lvardefs": [

		]
	},
	{
		"name": "destruct_PDFDevice",
		"ident": 17,
		"order": 10,
		"pvardefs": [

		],
		"lvardefs": [

		]
	},
	{
		"name": "destruct_OSpell2",
		"ident": 19,
		"order": 11,
		"pvardefs": [

		],
		"lvardefs": [

		]
	},
	{
		"name": "destruct_OWrite",
		"ident": 20,
		"order": 12,
		"pvardefs": [

		],
		"lvardefs": [

		]
	},
	{
		"name": "checkStudio",
		"ident": 13,
		"order": 13,
		"pvardefs": [

		],
		"lvardefs": [
			{
				"name": "major",
				"order": 2,
				"type": "kInteger",
				"subtype": "k32bitint",
				"sublen": 0
			},
			{
				"name": "minor1",
				"order": 3,
				"type": "kInteger",
				"subtype": "k32bitint",
				"sublen": 0
			},
			{
				"name": "minor2",
				"order": 4,
				"type": "kInteger",
				"subtype": "k32bitint",
				"sublen": 0
			},
			{
				"name": "minor3",
				"order": 5,
				"type": "kInteger",
				"subtype": "k32bitint",
				"sublen": 0
			},
			{
				"name": "version",
				"order": 1,
				"type": "kCharacter",
				"subtype": "kSimplechar",
				"sublen": 100000000
			}
		]
	},
	{
		"name": "checkExternals",
		"ident": 10,
		"order": 14,
		"pvardefs": [

		],
		"lvardefs": [
			{
				"name": "do_quit",
				"order": 8,
				"type": "kBoolean",
				"subtype": 0,
				"sublen": 0,
				"initval": "kFalse"
			},
			{
				"name": "error_message",
				"order": 4,
				"type": "kCharacter",
				"subtype": "kSimplechar",
				"sublen": 100000000
			},
			{
				"name": "file_ext_webcomp",
				"order": 6,
				"type": "kCharacter",
				"subtype": "kSimplechar",
				"sublen": 100000000
			},
			{
				"name": "file_ext_xcomp",
				"order": 3,
				"type": "kCharacter",
				"subtype": "kSimplechar",
				"sublen": 100000000
			},
			{
				"name": "ignore",
				"order": 9,
				"type": "kCharacter",
				"subtype": "kSimplechar",
				"sublen": 100000000
			},
			{
				"name": "ignore_error_message",
				"order": 10,
				"type": "kCharacter",
				"subtype": "kSimplechar",
				"sublen": 100000000,
				"desc": "used when we want to ignore errors CHANGE_2014_02_11__1"
			},
			{
				"name": "iref",
				"order": 7,
				"type": "kItemref",
				"subtype": "",
				"sublen": 0
			},
			{
				"name": "path",
				"order": 5,
				"type": "kCharacter",
				"subtype": "kSimplechar",
				"sublen": 100000000
			},
			{
				"name": "path_webcomp",
				"order": 2,
				"type": "kCharacter",
				"subtype": "kSimplechar",
				"sublen": 100000000
			},
			{
				"name": "path_xcomp",
				"order": 1,
				"type": "kCharacter",
				"subtype": "kSimplechar",
				"sublen": 100000000
			}
		]
	},
	{
		"name": "checkExternalFile",
		"ident": 23,
		"order": 15,
		"pvardefs": [
			{
				"name": "pFileName",
				"order": 1,
				"type": "kCharacter",
				"subtype": "kSimplechar",
				"sublen": 100000000,
				"param": 1
			},
			{
				"name": "pIsWebComp",
				"order": 2,
				"type": "kBoolean",
				"subtype": 0,
				"sublen": 0,
				"param": 2
			},
			{
				"name": "pErrorText",
				"order": 8,
				"type": "kFieldreference",
				"subtype": 0,
				"sublen": 0,
				"param": 3
			}
		],
		"lvardefs": [
			{
				"name": "path",
				"order": 4,
				"type": "kCharacter",
				"subtype": "kSimplechar",
				"sublen": 100000000
			},
			{
				"name": "_dir",
				"order": 5,
				"type": "kCharacter",
				"subtype": "kSimplechar",
				"sublen": 100000000
			},
			{
				"name": "_drive",
				"order": 3,
				"type": "kCharacter",
				"subtype": "kSimplechar",
				"sublen": 100000000
			},
			{
				"name": "_ext",
				"order": 7,
				"type": "kCharacter",
				"subtype": "kSimplechar",
				"sublen": 100000000
			},
			{
				"name": "_file",
				"order": 6,
				"type": "kCharacter",
				"subtype": "kSimplechar",
				"sublen": 100000000
			}
		]
	},
	{
		"name": "checkExternalVersionNew",
		"ident": 25,
		"order": 17,
		"pvardefs": [
			{
				"name": "pLibName",
				"order": 1,
				"type": "kCharacter",
				"subtype": "kSimplechar",
				"sublen": 100000000,
				"param": 1
			},
			{
				"name": "pFileName",
				"order": 5,
				"type": "kCharacter",
				"subtype": "kSimplechar",
				"sublen": 100000000,
				"param": 2
			},
			{
				"name": "pMinVersion",
				"order": 3,
				"type": "kInteger",
				"subtype": "k32bitint",
				"sublen": 0,
				"param": 3
			},
			{
				"name": "pErrorText",
				"order": 4,
				"type": "kFieldreference",
				"subtype": 0,
				"sublen": 0,
				"param": 4
			}
		],
		"lvardefs": [
			{
				"name": "externalVersion",
				"order": 9,
				"type": "kInteger",
				"subtype": "k32bitint",
				"sublen": 0
			},
			{
				"name": "externalVersionStudio",
				"order": 8,
				"type": "kInteger",
				"subtype": "k32bitint",
				"sublen": 0
			},
			{
				"name": "iref",
				"order": 2,
				"type": "kItemref",
				"subtype": "",
				"sublen": 0
			},
			{
				"name": "studio_version",
				"order": 11,
				"type": "kInteger",
				"subtype": "k32bitint",
				"sublen": 0
			},
			{
				"name": "version",
				"order": 10,
				"type": "kCharacter",
				"subtype": "kSimplechar",
				"sublen": 100000000,
				"initval": "iref.$version"
			}
		]
	},
	{
		"name": "-- OSpell2 - handling database dictionaries",
		"ident": 11,
		"order": 18,
		"pvardefs": [

		],
		"lvardefs": [

		],
		"empty": true
	},
	{
		"name": "$memlexcreate",
		"ident": 6,
		"order": 19,
		"pvardefs": [
			{
				"name": "pLexName",
				"order": 1,
				"type": "kCharacter",
				"subtype": "kSimplechar",
				"sublen": 100000000,
				"param": 1
			}
		],
		"lvardefs": [

		]
	},
	{
		"name": "$memlexdelete",
		"ident": 5,
		"order": 20,
		"pvardefs": [
			{
				"name": "pLexName",
				"order": 1,
				"type": "kCharacter",
				"subtype": "kSimplechar",
				"sublen": 100000000,
				"param": 1
			}
		],
		"lvardefs": [

		]
	},
	{
		"name": "$memlexsave",
		"ident": 3,
		"order": 21,
		"pvardefs": [
			{
				"name": "pLexName",
				"order": 3,
				"type": "kCharacter",
				"subtype": "kSimplechar",
				"sublen": 100000000,
				"param": 1
			},
			{
				"name": "pLexLangID",
				"order": 1,
				"type": "kInteger",
				"subtype": "k32bitint",
				"sublen": 0,
				"param": 2
			},
			{
				"name": "pLexWordList",
				"order": 2,
				"type": "kList",
				"subtype": "",
				"sublen": 0,
				"param": 3
			}
		],
		"lvardefs": [

		]
	},
	{
		"name": "$memlexload",
		"ident": 4,
		"order": 22,
		"pvardefs": [
			{
				"name": "pLexName",
				"order": 1,
				"type": "kCharacter",
				"subtype": "kSimplechar",
				"sublen": 100000000,
				"param": 1
			},
			{
				"name": "pLexLangID",
				"order": 2,
				"type": "kFieldreference",
				"subtype": 0,
				"sublen": 0,
				"param": 2
			},
			{
				"name": "pLexWordList",
				"order": 3,
				"type": "kFieldreference",
				"subtype": 0,
				"sublen": 0,
				"param": 3
			}
		],
		"lvardefs": [

		]
	},
	{
		"name": "$memlexappendlist",
		"ident": 2,
		"order": 23,
		"pvardefs": [
			{
				"name": "pList",
				"order": 1,
				"type": "kFieldreference",
				"subtype": 0,
				"sublen": 0,
				"param": 1
			}
		],
		"lvardefs": [

		]
	},
	{
		"name": "-- OWrite - utility methods",
		"ident": 7,
		"order": 24,
		"pvardefs": [

		],
		"lvardefs": [

		],
		"empty": true
	},
	{
		"name": "$readfontmap",
		"ident": 8,
		"order": 25,
		"pvardefs": [
			{
				"name": "pOutList",
				"order": 1,
				"type": "kFieldreference",
				"subtype": 0,
				"sublen": 0,
				"param": 1,
				"desc": "returns the list of fonts"
			},
			{
				"name": "pOutRestrictFonts",
				"order": 4,
				"type": "kFieldreference",
				"subtype": 0,
				"sublen": 0,
				"param": 2,
				"desc": "specifies if map limits fonts that can be used in OWrite ;; CHANGE_V3A12"
			}
		],
		"lvardefs": [
			{
				"name": "fontmapBin",
				"order": 3,
				"type": "kBinary",
				"subtype": 0,
				"sublen": 100000000
			},
			{
				"name": "fontmapFile",
				"order": 2,
				"type": "kObject",
				"subtype": ".FileOps.FileOps",
				"sublen": 0
			},
			{
				"name": "fontmapLoaded",
				"order": 7,
				"type": "kBoolean",
				"subtype": 0,
				"sublen": 0
			},
			{
				"name": "fontmapRow",
				"order": 6,
				"type": "kRow",
				"subtype": "",
				"sublen": 0
			}
		]
	},
	{
		"name": "$writefontmap",
		"ident": 9,
		"order": 26,
		"pvardefs": [
			{
				"name": "pInList",
				"order": 1,
				"type": "kFieldreference",
				"subtype": 0,
				"sublen": 0,
				"param": 1
			},
			{
				"name": "pInRestrictFonts",
				"order": 4,
				"type": "kBoolean",
				"subtype": 0,
				"sublen": 0,
				"param": 2,
				"desc": "specifies if map limits fonts that can be used in OWrite ;; CHANGE_V3A12"
			}
		],
		"lvardefs": [
			{
				"name": "fontmapBin",
				"order": 2,
				"type": "kBinary",
				"subtype": 0,
				"sublen": 100000000
			},
			{
				"name": "fontmapFile",
				"order": 3,
				"type": "kObject",
				"subtype": ".FileOps.FileOps",
				"sublen": 0
			},
			{
				"name": "fontmapRow",
				"order": 5,
				"type": "kRow",
				"subtype": "",
				"sublen": 0,
				"desc": "new row var for writing font map to disk CHANGE_V3A12"
			},
			{
				"name": "List",
				"order": 6,
				"type": "kList",
				"subtype": "",
				"sublen": 0,
				"desc": "used for defining fontmapRow ;; CHANGE_V3A12"
			},
			{
				"name": "RestrictFonts",
				"order": 7,
				"type": "kBoolean",
				"subtype": 0,
				"sublen": 0,
				"desc": "used for defining fontmapRow ;; CHANGE_V3A12"
			}
		]
	},
	{
		"name": "$showmessage",
		"ident": 24,
		"order": 27,
		"pvardefs": [
			{
				"name": "pTitle",
				"order": 1,
				"type": "kCharacter",
				"subtype": "kSimplechar",
				"sublen": 100000000,
				"param": 1
			},
			{
				"name": "pMessage",
				"order": 2,
				"type": "kCharacter",
				"subtype": "kSimplechar",
				"sublen": 100000000,
				"param": 2
			}
		],
		"lvardefs": [

		]
	},
	{
		"name": "$openurl",
		"ident": 27,
		"order": 28,
		"desc": "23_09_2011_CHANGE_1 new method",
		"pvardefs": [
			{
				"name": "pURL",
				"order": 3,
				"type": "kCharacter",
				"subtype": "kSimplechar",
				"sublen": 100000000,
				"param": 1,
				"desc": "fully qualified URL to be opened in the default browser"
			}
		],
		"lvardefs": [
			{
				"name": "error",
				"order": 4,
				"type": "kInteger",
				"subtype": "k32bitint",
				"sublen": 0
			},
			{
				"name": "results",
				"order": 2,
				"type": "kCharacter",
				"subtype": "kSimplechar",
				"sublen": 100000000
			},
			{
				"name": "script",
				"order": 1,
				"type": "kCharacter",
				"subtype": "kSimplechar",
				"sublen": 10000
			}
		]
	},
	{
		"name": "New Method",
		"ident": 26,
		"order": 29,
		"pvardefs": [

		],
		"lvardefs": [

		]
	}
]
