[
	{
		"name": "$construct",
		"ident": 1,
		"order": 1,
		"pvardefs": [
			{
				"name": "pEditObjRef",
				"order": 1,
				"type": "kItemref",
				"subtype": "",
				"sublen": 0,
				"param": 1
			}
		],
		"lvardefs": [

		]
	},
	{
		"name": "$destruct",
		"ident": 2,
		"order": 2,
		"pvardefs": [

		],
		"lvardefs": [

		]
	},
	{
		"name": "$modified",
		"ident": 4,
		"order": 3,
		"desc": "renamed CHANGE_28JUL08_1",
		"pvardefs": [

		],
		"lvardefs": [
			{
				"name": "changed",
				"order": 1,
				"type": "kBoolean",
				"subtype": 0,
				"sublen": 0
			}
		]
	},
	{
		"name": "load",
		"ident": 0,
		"order": 4,
		"pvardefs": [

		],
		"lvardefs": [

		]
	},
	{
		"name": "apply",
		"ident": 3,
		"order": 5,
		"pvardefs": [

		],
		"lvardefs": [

		]
	},
	{
		"name": "styleChanged",
		"ident": 5,
		"order": 6,
		"pvardefs": [

		],
		"lvardefs": [

		]
	},
	{
		"name": "removeCurrentStyle",
		"ident": 7,
		"order": 7,
		"pvardefs": [

		],
		"lvardefs": [
			{
				"name": "error",
				"order": 1,
				"type": "kInteger",
				"subtype": "k32bitint",
				"sublen": 0
			}
		]
	},
	{
		"name": "removeUnusedStyles",
		"ident": 6,
		"order": 8,
		"pvardefs": [

		],
		"lvardefs": [
			{
				"name": "delStyles",
				"order": 5,
				"type": "kCharacter",
				"subtype": "kSimplechar",
				"sublen": 100000000
			},
			{
				"name": "error",
				"order": 3,
				"type": "kInteger",
				"subtype": "k32bitint",
				"sublen": 0
			},
			{
				"name": "name",
				"order": 2,
				"type": "kCharacter",
				"subtype": "kSimplechar",
				"sublen": 100000000
			},
			{
				"name": "savedCurStyle",
				"order": 1,
				"type": "kCharacter",
				"subtype": "kSimplechar",
				"sublen": 100000000
			}
		]
	},
	{
		"name": "addStyle",
		"ident": 8,
		"order": 9,
		"pvardefs": [

		],
		"lvardefs": [
			{
				"name": "name",
				"order": 1,
				"type": "kCharacter",
				"subtype": "kSimplechar",
				"sublen": 100000000
			}
		]
	}
]
