{
	"ident": 1143,
	"order": 16418,
	"objtype": "kText",
	"properties": {
		"align": "kLeftJst",
		"backcolor": "kColorBackFill",
		"backpattern": 15,
		"designactive": true,
		"edgefloat": "kEFnone",
		"fieldstyle": "CtrlLabelLarge",
		"font": 2,
		"fontsize": 0,
		"fontstyle": "kPlain",
		"forecolor": "kColorForeFill",
		"height": 17,
		"left": 49,
		"objlink": 65537,
		"text": {
			"type": 14,
			"calc": "Font Handling"
		},
		"textcolor": "kColorWindowText",
		"top": 199,
		"userinfo": "",
		"vertcentertext": false,
		"visible": true,
		"width": 151
	}
}
